[
  {
    "full_name": "supabase/supabase",
    "stargazers_count": 20325,
    "open_issues_count": 152,
    "forks_count": 1025
  },
  {
    "full_name": "drewclem/protege",
    "stargazers_count": 60,
    "open_issues_count": 23,
    "forks_count": 42
  },
  {
    "full_name": "ronakganatra/awesome-developer-marketing",
    "stargazers_count": 93,
    "open_issues_count": 0,
    "forks_count": 3
  },
  {
    "full_name": "surface-ui/surface",
    "stargazers_count": 1474,
    "open_issues_count": 24,
    "forks_count": 88
  },
  {
    "full_name": "11ty/eleventy",
    "stargazers_count": 10463,
    "open_issues_count": 419,
    "forks_count": 303
  },
  {
    "full_name": "foambubble/foam",
    "stargazers_count": 10614,
    "open_issues_count": 133,
    "forks_count": 448
  },
  {
    "full_name": "jonathanyeong/personal-website",
    "stargazers_count": 2,
    "open_issues_count": 12,
    "forks_count": 0
  },
  {
    "full_name": "mikejahn/support-your-local-businesses",
    "stargazers_count": 4,
    "open_issues_count": 9,
    "forks_count": 3
  },
  {
    "full_name": "MunGell/awesome-for-beginners",
    "stargazers_count": 35627,
    "open_issues_count": 58,
    "forks_count": 5223
  },
  {
    "full_name": "HabitRPG/habitica",
    "stargazers_count": 8574,
    "open_issues_count": 228,
    "forks_count": 3349
  },
  {
    "full_name": "seattlerb/hoe",
    "stargazers_count": 274,
    "open_issues_count": 8,
    "forks_count": 64
  },
  {
    "full_name": "there4/markdown-resume",
    "stargazers_count": 1648,
    "open_issues_count": 18,
    "forks_count": 529
  },
  {
    "full_name": "vuejs/vuepress",
    "stargazers_count": 19480,
    "open_issues_count": 539,
    "forks_count": 4226
  },
  {
    "full_name": "gridsome/gridsome",
    "stargazers_count": 7934,
    "open_issues_count": 541,
    "forks_count": 467
  },
  {
    "full_name": "gohugoio/hugo",
    "stargazers_count": 54717,
    "open_issues_count": 698,
    "forks_count": 6222
  },
  {
    "full_name": "probot/probot",
    "stargazers_count": 7231,
    "open_issues_count": 28,
    "forks_count": 864
  },
  {
    "full_name": "nhn/tui.editor",
    "stargazers_count": 13736,
    "open_issues_count": 257,
    "forks_count": 1289
  },
  {
    "full_name": "whuang8/herp-derp",
    "stargazers_count": 1,
    "open_issues_count": 0,
    "forks_count": 0
  },
  {
    "full_name": "netlify/netlify-cms",
    "stargazers_count": 14567,
    "open_issues_count": 625,
    "forks_count": 2526
  },
  {
    "full_name": "DopplerHQ/awesome-interview-questions",
    "stargazers_count": 43795,
    "open_issues_count": 6,
    "forks_count": 6391
  },
  {
    "full_name": "octobox/octobox",
    "stargazers_count": 4105,
    "open_issues_count": 28,
    "forks_count": 361
  },
  {
    "full_name": "maestrano/maestrano-connector-rails",
    "stargazers_count": 2,
    "open_issues_count": 6,
    "forks_count": 15
  },
  {
    "full_name": "yeoman/generator-angular",
    "stargazers_count": 5828,
    "open_issues_count": 90,
    "forks_count": 1524
  },
  {
    "full_name": "engineerapart/TheRemoteFreelancer",
    "stargazers_count": 6409,
    "open_issues_count": 3,
    "forks_count": 374
  },
  {
    "full_name": "thechangelog/changelog.com",
    "stargazers_count": 2323,
    "open_issues_count": 31,
    "forks_count": 218
  },
  {
    "full_name": "quilljs/quill",
    "stargazers_count": 31067,
    "open_issues_count": 1144,
    "forks_count": 2600
  },
  {
    "full_name": "ampproject/amphtml",
    "stargazers_count": 14736,
    "open_issues_count": 1796,
    "forks_count": 3885
  },
  {
    "full_name": "SpinaCMS/Spina",
    "stargazers_count": 1899,
    "open_issues_count": 48,
    "forks_count": 346
  },
  {
    "full_name": "rails-oceania/roro",
    "stargazers_count": 171,
    "open_issues_count": 24,
    "forks_count": 10
  },
  {
    "full_name": "basecamp/trix",
    "stargazers_count": 16446,
    "open_issues_count": 50,
    "forks_count": 973
  }
]